opentelemetry/util/http/__init__.py
opentelemetry/util/http/httplib.py
opentelemetry/util/http/version.py
opentelemetry_util_http-0.33b0.dist-info/METADATA
opentelemetry_util_http-0.33b0.dist-info/WHEEL
opentelemetry_util_http-0.33b0.dist-info/top_level.txt
opentelemetry_util_http-0.33b0.dist-info/RECORD
