Metadata-Version: 2.1
Name: opentelemetry-util-http
Version: 0.33b0
Summary: Web util for OpenTelemetry
Home-page: https://github.com/open-telemetry/opentelemetry-python-contrib/util/opentelemetry-util-http
Author: OpenTelemetry Authors
Author-email: cncf-opentelemetry-contributors@lists.cncf.io
License: Apache-2.0
Platform: any
Classifier: Development Status :: 4 - Beta
Classifier: Intended Audience :: Developers
Classifier: License :: OSI Approved :: Apache Software License
Classifier: Programming Language :: Python
Classifier: Programming Language :: Python :: 3
Classifier: Programming Language :: Python :: 3.6
Classifier: Programming Language :: Python :: 3.7
Classifier: Programming Language :: Python :: 3.8
Classifier: Programming Language :: Python :: 3.9
Classifier: Programming Language :: Python :: 3.10
Requires-Python: >=3.6
